neuralex/__init__.py
neuralex/client.py
neuralex/exceptions.py
neuralex/models.py
neuralex-0.2.0.dist-info/licenses/LICENSE
neuralex-0.2.0.dist-info/METADATA
neuralex-0.2.0.dist-info/WHEEL
neuralex-0.2.0.dist-info/top_level.txt
neuralex-0.2.0.dist-info/RECORD
