Metadata-Version: 2.4
Name: neuralex
Version: 0.2.0
Summary: Official Python client library for NeuraLex API
Author-email: NeuraLex <support@neuralex.ca>
License: MIT
Project-URL: Homepage, https://neuralex.ca
Project-URL: Documentation, https://neuralex.ca/docs/api
Project-URL: Repository, https://github.com/pavel604/neuralex-lib
Project-URL: Bug Tracker, https://github.com/pavel604/neuralex-lib/issues
Keywords: embeddings,vector,search,ai,ml,neuralex,semantic-search,hybrid-search,similarity-search,rag,retrieval,pgvector,pinecone,qdrant,weaviate,milvus,chroma,dense-retrieval,transformers,nlp,machine-learning
Classifier: Development Status :: 3 - Alpha
Classifier: Intended Audience :: Developers
Classifier: License :: OSI Approved :: MIT License
Classifier: Programming Language :: Python :: 3
Classifier: Programming Language :: Python :: 3.8
Classifier: Programming Language :: Python :: 3.9
Classifier: Programming Language :: Python :: 3.10
Classifier: Programming Language :: Python :: 3.11
Classifier: Programming Language :: Python :: 3.12
Classifier: Topic :: Scientific/Engineering :: Artificial Intelligence
Requires-Python: >=3.8
License-File: LICENSE
Requires-Dist: httpx>=0.24.0
Requires-Dist: pydantic>=2.0.0
Provides-Extra: dev
Requires-Dist: pytest>=7.0.0; extra == "dev"
Requires-Dist: pytest-asyncio>=0.21.0; extra == "dev"
Requires-Dist: black>=23.0.0; extra == "dev"
Requires-Dist: mypy>=1.0.0; extra == "dev"
Requires-Dist: ruff>=0.1.0; extra == "dev"
Dynamic: license-file
